netbox_floorplan/__init__.py
netbox_floorplan/admin.py
netbox_floorplan/filtersets.py
netbox_floorplan/forms.py
netbox_floorplan/models.py
netbox_floorplan/navigation.py
netbox_floorplan/tables.py
netbox_floorplan/urls.py
netbox_floorplan/utils.py
netbox_floorplan/version.py
netbox_floorplan/views.py
netbox_floorplan/api/__init__.py
netbox_floorplan/api/serializers.py
netbox_floorplan/api/urls.py
netbox_floorplan/api/views.py
netbox_floorplan/migrations/0001_initial.py
netbox_floorplan/migrations/0002_floorplan_measurement_unit_alter_floorplan_scale.py
netbox_floorplan/migrations/0003_floorplan_canvas.py
netbox_floorplan/migrations/0004_alter_floorplan_options.py
netbox_floorplan/migrations/0005_alter_floorplan_site.py
netbox_floorplan/migrations/0006_delete_floorplanobject.py
netbox_floorplan/migrations/0007_alter_floorplan_options_and_more.py
netbox_floorplan/migrations/0008_floorplanimage.py
netbox_floorplan/migrations/0009_floorplanimage_file.py
netbox_floorplan/migrations/0010_floorplanimage_external_url.py
netbox_floorplan/migrations/0011_floorplanimage_comments.py
netbox_floorplan/migrations/0012_alter_floorplan_options_and_more.py
netbox_floorplan/migrations/__init__.py
netbox_floorplan/static/netbox_floorplan/floorplan/edit.js
netbox_floorplan/static/netbox_floorplan/floorplan/utils.js
netbox_floorplan/static/netbox_floorplan/floorplan/view.js
netbox_floorplan/static/netbox_floorplan/vendors/fabric-js-6.0.2.js
netbox_floorplan/static/netbox_floorplan/vendors/htmx.min.js
netbox_floorplan/static/netbox_floorplan/vendors/jquery-3.7.1.js
netbox_floorplan/templates/netbox_floorplan/floorplan.html
netbox_floorplan/templates/netbox_floorplan/floorplan_edit.html
netbox_floorplan/templates/netbox_floorplan/floorplan_list.html
netbox_floorplan/templates/netbox_floorplan/floorplan_ui_listview.html
netbox_floorplan/templates/netbox_floorplan/floorplan_view.html
netbox_floorplan/templates/netbox_floorplan/floorplanimage.html
netbox_floorplan_plugin-0.9.0.dist-info/licenses/LICENSE
netbox_floorplan_plugin-0.9.0.dist-info/METADATA
netbox_floorplan_plugin-0.9.0.dist-info/WHEEL
netbox_floorplan_plugin-0.9.0.dist-info/top_level.txt
netbox_floorplan_plugin-0.9.0.dist-info/RECORD
