Metadata-Version: 2.4
Name: netbox-floorplan-plugin
Version: 0.9.0
Summary: Netbox Plugin to support graphical floorplans
Home-page: https://github.com/netbox-community/netbox-floorplan-plugin.git
Author: Tony Nealon
Author-email: tony@worksystems.co.nz
License: LGPLv3+
License-File: LICENSE
Dynamic: author
Dynamic: author-email
Dynamic: description
Dynamic: description-content-type
Dynamic: home-page
Dynamic: license
Dynamic: license-file
Dynamic: summary
